{
	"@type":"Hierarchy",
	"Name":"A_Version",
	"Elements":
	[
		{
			"Name":"Open Versions",
			"Type":"Consolidated"
		},
		{
			"Name":"Actual",
			"Type":"Numeric"
		},
		{
			"Name":"Version 1",
			"Type":"Numeric"
		},
		{
			"Name":"Archived Versions",
			"Type":"Consolidated"
		},
		{
			"Name":"Consolidation Versions",
			"Type":"Consolidated"
		},
		{
			"Name":"Variances Analysis",
			"Type":"Consolidated"
		},
		{
			"Name":"Variance",
			"Type":"Numeric"
		},
		{
			"Name":"Variance%",
			"Type":"Numeric"
		},
		{
			"Name":"Performance Variance",
			"Type":"Numeric"
		},
		{
			"Name":"Ccy Exchange Variance",
			"Type":"Numeric"
		},
		{
			"Name":"Forecast",
			"Type":"Numeric"
		},
		{
			"Name":"Target",
			"Type":"Numeric"
		},
		{
			"Name":"Prior Year Actual",
			"Type":"Numeric"
		},
		{
			"Name":"Rate Variance",
			"Type":"Numeric"
		},
		{
			"Name":"Volume Variance",
			"Type":"Numeric"
		},
		{
			"Name":"Forecast_Stat",
			"Type":"Numeric"
		},
		{
			"Name":"Prior Month",
			"Type":"Numeric"
		},
		{
			"Name":"Historique",
			"Type":"Numeric"
		},
		{
			"Name":"Commitment",
			"Type":"Numeric"
		},
		{
			"Name":"Budget V2",
			"Type":"Numeric"
		},
		{
			"Name":"V1",
			"Type":"Numeric"
		},
		{
			"Name":"V2",
			"Type":"Numeric"
		},
		{
			"Name":"V3",
			"Type":"Numeric"
		},
		{
			"Name":"V4",
			"Type":"Numeric"
		},
		{
			"Name":"PY Forecast",
			"Type":"Numeric"
		},
		{
			"Name":"Budget V3",
			"Type":"Numeric"
		},
		{
			"Name":"Forecast Juin",
			"Type":"Numeric"
		},
		{
			"Name":"Budget V4",
			"Type":"Numeric"
		},
		{
			"Name":"Budget V5",
			"Type":"Numeric"
		}
	],
	"Edges":
	[
		{
			"ParentName":"Open Versions",
			"ComponentName":"Actual",
			"Weight":0
		},
		{
			"ParentName":"Open Versions",
			"ComponentName":"Target",
			"Weight":0
		},
		{
			"ParentName":"Open Versions",
			"ComponentName":"Version 1",
			"Weight":0
		},
		{
			"ParentName":"Open Versions",
			"ComponentName":"Commitment",
			"Weight":1
		},
		{
			"ParentName":"Open Versions",
			"ComponentName":"Forecast",
			"Weight":0
		},
		{
			"ParentName":"Open Versions",
			"ComponentName":"Forecast_Stat",
			"Weight":1
		},
		{
			"ParentName":"Archived Versions",
			"ComponentName":"Prior Year Actual",
			"Weight":1
		},
		{
			"ParentName":"Archived Versions",
			"ComponentName":"PY Forecast",
			"Weight":1
		},
		{
			"ParentName":"Archived Versions",
			"ComponentName":"Prior Month",
			"Weight":1
		},
		{
			"ParentName":"Archived Versions",
			"ComponentName":"Historique",
			"Weight":0
		},
		{
			"ParentName":"Archived Versions",
			"ComponentName":"Budget V2",
			"Weight":0
		},
		{
			"ParentName":"Archived Versions",
			"ComponentName":"Budget V3",
			"Weight":0
		},
		{
			"ParentName":"Archived Versions",
			"ComponentName":"Forecast Juin",
			"Weight":0
		},
		{
			"ParentName":"Archived Versions",
			"ComponentName":"Budget V4",
			"Weight":0
		},
		{
			"ParentName":"Archived Versions",
			"ComponentName":"Budget V5",
			"Weight":0
		},
		{
			"ParentName":"Consolidation Versions",
			"ComponentName":"V1",
			"Weight":1
		},
		{
			"ParentName":"Consolidation Versions",
			"ComponentName":"V2",
			"Weight":1
		},
		{
			"ParentName":"Consolidation Versions",
			"ComponentName":"V3",
			"Weight":1
		},
		{
			"ParentName":"Consolidation Versions",
			"ComponentName":"V4",
			"Weight":1
		},
		{
			"ParentName":"Variances Analysis",
			"ComponentName":"Variance",
			"Weight":1
		},
		{
			"ParentName":"Variances Analysis",
			"ComponentName":"Variance%",
			"Weight":0
		},
		{
			"ParentName":"Variances Analysis",
			"ComponentName":"Performance Variance",
			"Weight":0
		},
		{
			"ParentName":"Variances Analysis",
			"ComponentName":"Ccy Exchange Variance",
			"Weight":0
		},
		{
			"ParentName":"Variances Analysis",
			"ComponentName":"Rate Variance",
			"Weight":0
		},
		{
			"ParentName":"Variances Analysis",
			"ComponentName":"Volume Variance",
			"Weight":0
		}
	],
	"Subsets@Code.links":
	[
		"A_Version.subsets/Actual.json",
		"A_Version.subsets/Actual Y-1.json",
		"A_Version.subsets/All Members.json",
		"A_Version.subsets/Analysis.json",
		"A_Version.subsets/Budget.json",
		"A_Version.subsets/Bud vs ActY1.json",
		"A_Version.subsets/Bud vs FcstY1.json",
		"A_Version.subsets/Closed Versions.json",
		"A_Version.subsets/Comp_Budget&Forecast.json",
		"A_Version.subsets/Comp_Budget_Reel.json",
		"A_Version.subsets/Comp_Obj_Budget_Reel.json",
		"A_Version.subsets/Comp_PYForecast&Budget.json",
		"A_Version.subsets/Comp_ReelN1&Budget.json",
		"A_Version.subsets/Comp_ReelN1&Budget&Forecast.json",
		"A_Version.subsets/Comp_ReelN1&Budget&Forecast&Reel.json",
		"A_Version.subsets/Comp_Target&Budget.json",
		"A_Version.subsets/Current.json",
		"A_Version.subsets/Default.json",
		"A_Version.subsets/Forecast.json",
		"A_Version.subsets/Open Versions.json",
		"A_Version.subsets/Target.json",
		"A_Version.subsets/Variance analysis.json",
		"A_Version.subsets/Versions Courantes et Archivées.json",
		"A_Version.subsets/zCopyFrom.json"
	]
}